ost_kyc_sdk_python/__init__.py
ost_kyc_sdk_python/services.py
ost_kyc_sdk_python/saas/__init__.py
ost_kyc_sdk_python/saas/base.py
ost_kyc_sdk_python/saas/manifest.py
ost_kyc_sdk_python/saas/users.py
ost_kyc_sdk_python/saas/users_kyc.py
ost_kyc_sdk_python/saas/users_kyc_details.py
ost_kyc_sdk_python/saas/validators.py
ost_kyc_sdk_python/util/__init__.py
ost_kyc_sdk_python/util/http_helper.py
ost_kyc_sdk_python/util/python_version.py
ost_kyc_sdk_python-2.0.2.dist-info/LICENSE.txt
ost_kyc_sdk_python-2.0.2.dist-info/METADATA
ost_kyc_sdk_python-2.0.2.dist-info/WHEEL
ost_kyc_sdk_python-2.0.2.dist-info/top_level.txt
ost_kyc_sdk_python-2.0.2.dist-info/RECORD
