Metadata-Version: 2.1
Name: ost-kyc-sdk-python
Version: 2.0.2
Summary: OST KYC SDK in python
Home-page: https://github.com/ostdotcom/ost-kyc-sdk-python
License: MIT
Platform: UNKNOWN
Requires-Dist: requests
